[{"album": "Groovin' High", "artist": "Dizzy Gillespie", "personnel": {"Curly Russell": ["bass"], "Sidney Catlett": ["drums"], "Charlie Parker": ["alto saxophone"], "Al Haig": ["piano"]}, "instrument": ["trumpet", "vocals"], "year": "1945", "label-id": "Savoy MG 12020"}, {"album": "In The Beginning", "artist": "Dizzy Gillespie", "personnel": {"Curly Russell": ["bass"], "Charlie Parker": ["alto saxophone"], "Al Haig": ["piano"], "Sarah Vaughan": ["vocals"], "Sidney Catlett": ["drums"]}, "instrument": ["trumpet", "vocals"], "year": "1945", "label-id": "Prestige PR 24030"}, {"album": "Birth Of The Bebop: Bird On Tenor 1943", "artist": "Charlie Parker", "personnel": {"Curly Russell": ["bass"], "Al Haig": ["piano"], "Stan Levey": ["drums"], "Don Byas": ["tenor saxophone"], "Dizzy Gillespie": ["trumpet"]}, "instrument": ["alto saxophone"], "year": "1945", "label-id": "Stash ST 260"}, {"album": "Bird's Eyes, Vol. 17 \u00a0(Philology", "artist": "Charlie Parker", "personnel": {"Curly Russell": ["bass"], "Al Haig": ["piano"], "Stan Levey": ["drums"], "Dizzy Gillespie": ["trumpet"], "Red Norvo": ["vibraphone"]}, "instrument": ["alto saxophone"], "year": "1945", "label-id": "It) W 847.2"}, {"album": "Town Hall, New York City, June 22, 1945", "personnel": {"Curly Russell": ["bass"], "Charlie Parker": ["alto saxophone"], "Al Haig": ["piano"], "Max Roach": ["drums"], "Sid Catlett": ["drums"], "Don Byas": ["tenor saxophone"], "Dizzy Gillespie": ["trumpet"]}, "artist": "Dizzy Gillespie/Charlie Parker", "label-id": "Uptown UPCD 27.51", "year": "1945"}, {"album": "Yardbird In Lotus Land \u00a0(Spotlite", "artist": "Charlie Parker", "personnel": {"Al Haig": ["piano"], "Stan Levey": ["drums"], "Milt Jackson": ["vibraphone"], "Ray Brown": ["bass"], "Ernie \"Bubbles\" Whitman": ["announcer"], "Dizzy Gillespie": ["trumpet"]}, "instrument": ["alto saxophone"], "year": "1945", "label-id": "E) SPJ 123"}, {"album": "Rappin' With Bird", "artist": "Charlie Parker", "personnel": {"Al Haig": ["piano"], "Stan Levey": ["drums"], "Milt Jackson": ["vibraphone"], "Ray Brown": ["bass"], "Luckey Tompson": ["tenor saxophone"], "Dizzy Gillespie": ["trumpet", "vocals"]}, "instrument": ["alto saxophone", "vocals"], "year": "1946", "label-id": "Meexa Discox 1776"}, {"album": "Dizzy's Delight", "artist": "Dizzy Gillespie", "personnel": {"a french horn": ["arranger"], "Al Haig": ["piano"], "+ 6 strings": ["arranger"], "a harp": ["arranger"], "4 woodwinds": ["arranger"], "Ray Brown": ["bass"], "Roy Hall": ["drums"], "Johnny Richards": ["arranger"]}, "instrument": ["trumpet"], "year": "1946", "label-id": "Phoenix Jazz LP 4"}, {"album": "Modern Jazz Trumpets \u00a0(Spotlite", "artist": "Dizzy Gillespie", "personnel": {"Al Haig": ["piano"], "Stan Levey": ["drums"], "Milt Jackson": ["vibraphone", "vocals"], "Ray Brown": ["bass"], "Lucky Thompson": ["tenor saxophone", "vocals"]}, "instrument": ["trumpet", "vocals"], "year": "1946", "label-id": "E) SPJ 132"}, {"album": "Dizzy Gillespie And Modern Trumpets", "personnel": {"Al Haig": ["piano"], "Stan Levey": ["drums"], "Milt Jackson": ["vibraphone", "vocals"], "Ray Brown": ["bass"], "Lucky Thompson": ["tenor saxophone", "vocals"], "Dizzy Gillespie": ["trumpet", "vocals"]}, "artist": "Various Artists", "label-id": "Dial LP 212", "year": "1946"}, {"album": "Dizzy Gillespie", "artist": "Dizzy Gillespie", "personnel": {"Al Haig": ["piano"], "Bill DeArango": ["guitar"], "Milt Jackson": ["vibraphone"], "J.C. Heard": ["drums"], "Ray Brown": ["bass"], "Don Byas": ["tenor saxophone"]}, "instrument": ["trumpet"], "year": "1946", "label-id": "RCA Victor LPV 530"}, {"album": "The Greatest Of Dizzy Gillespie", "artist": "Dizzy Gillespie", "personnel": {"Al Haig": ["piano"], "Bill DeArango": ["guitar"], "Milt Jackson": ["vibraphone"], "J.C. Heard": ["drums"], "Ray Brown": ["bass"], "Don Byas": ["tenor saxophone"]}, "instrument": ["trumpet"], "year": "1946", "label-id": "RCA Victor LPM 2398"}, {"album": "Frog And Mule / Spang", "artist": "Ben Webster", "personnel": {"John Simmons": ["bass"], "Sidney Catlett": ["drums"], "Bill DeArango": ["guitar"], "Al Haig": ["piano"]}, "instrument": ["tenor saxophone"], "year": "1946", "label-id": "Haven 805"}, {"album": "Doctor Keets / Park And Tilford Blues", "artist": "Ben Webster", "personnel": {"John Simmons": ["bass"], "Sidney Catlett": ["drums"], "Bill DeArango": ["guitar"], "Al Haig": ["piano"]}, "instrument": ["tenor saxophone"], "year": "1946", "label-id": "Haven 804"}, {"album": "Complete Keynote Collection \u00a0(Mercury", "personnel": {"Curly Russell": ["bass"], "Al Haig": ["piano"], "Stan Levey": ["drums"], "Neal Hefti": ["arranger"], "Buddy Stewart": ["vocals"], "Dave Lambert": ["vocals"], "Red Rodney": ["trumpet"]}, "artist": "Various Artists", "label-id": "J) 18PJ-1051/71", "year": "1946"}, {"album": "Nostalgia", "artist": "Fats Navarro", "personnel": {"Gene Ramey": ["bass"], "Al Haig": ["piano"], "Denzil Best": ["drums"], "Huey Long": ["guitar"], "Eddie \"Lockjaw\" Davis": ["tenor saxophone"]}, "instrument": ["trumpet"], "year": "1946", "label-id": "Savoy MG 12133"}, {"album": "In The Beginning Bebop!", "personnel": {"Gene Ramey": ["bass"], "Al Haig": ["piano"], "Denzil Best": ["drums"], "Huey Long": ["guitar"], "Eddie \"Lockjaw\" Davis": ["tenor saxophone"], "Fats Navarro": ["trumpet"]}, "artist": "Various Artists", "label-id": "Savoy MG 12119", "year": "1946"}, {"album": "The Advance Guard Of The '40s", "personnel": {"Serge Chaloff": ["baritone saxophone"], "Al Haig": ["piano"], "Chubby Jackson": ["bass"], "Allen Eager": ["tenor saxophone"], "Red Rodney": ["trumpet"], "Tiny Kahn": ["drums"]}, "artist": "Various Artists", "label-id": "EmArcy MG 36016", "year": "1947"}, {"album": "You Wear Love So Well / If Love Is Trouble", "artist": "Buddy Stewart", "personnel": {"Charlie Perry": ["drums"], "Don Russo or Clyde Lombardi": ["bass"], "Al Haig": ["piano"]}, "instrument": ["vocals"], "year": "1948", "label-id": "Sittin' In With 502"}, {"album": "Al Haig Meets The Master Saxes, Vol. 2 \u00a0(Spotlite", "artist": "Al Haig", "personnel": {"Wardell Gray": ["tenor saxophone"], "Jimmy Raney": ["guitar"], "Buddy Stewart": ["vocals"], "Charlie Perry": ["drums"], "Don Russo or Clyde Lombardi": ["bass"]}, "instrument": ["piano"], "year": "1948", "label-id": "E) SPJ 140"}, {"album": "Al Haig Meets The Master Saxes, Vol. 1 \u00a0(Spotlite", "artist": "Al Haig", "personnel": {"Wardell Gray": ["tenor saxophone"], "Clyde Lombardi": ["bass"], "Tiny Kahn": ["drums"]}, "instrument": ["piano"], "year": "1948", "label-id": "E) SPJ 139"}, {"album": "A Look At Yesterday", "personnel": {"Wardell Gray": ["tenor saxophone"], "Clyde Lombardi": ["bass"], "Tiny Kahn": ["drums"], "Al Haig": ["piano"]}, "artist": "Stan Getz", "label-id": "Mainstream 56025", "year": "1948"}, {"album": "Al Haig Meets The Master Saxes, Vol. 3 \u00a0(Spotlite", "artist": "Al Haig", "personnel": {"Jimmy Raney": ["guitar", "vocals"], "Charlie Perry": ["drums"], "Don Russo": ["bass"], "Terry Swope": ["vocals"]}, "instrument": ["piano"], "year": "1948", "label-id": "E) SPJ 143"}, {"album": "Bird At The Roost, Vol. 1", "artist": "Charlie Parker", "personnel": {"Miles Davis": ["trumpet"], "Max Roach": ["drums"], "Tommy Potter": ["bass"], "Al Haig": ["piano"]}, "instrument": ["alto saxophone"], "year": "1948", "label-id": "Savoy ZDS 4411/12"}, {"album": "Newly Discovered Sides By Charlie Parker", "artist": "Charlie Parker", "personnel": {"Miles Davis": ["trumpet"], "Max Roach": ["drums"], "Tommy Potter": ["bass"], "Al Haig": ["piano"]}, "instrument": ["alto saxophone"], "year": "1948", "label-id": "Savoy MG 12186"}, {"album": "The 'Bird' Returns", "artist": "Charlie Parker", "personnel": {"Miles Davis": ["trumpet"], "Max Roach": ["drums"], "Tommy Potter": ["bass"], "Al Haig": ["piano"]}, "instrument": ["alto saxophone"], "year": "1948", "label-id": "Savoy MG 12179"}, {"album": "A Look At Yesterday", "artist": "Stan Getz", "personnel": {"Jimmy Raney": ["guitar"], "Charlie Perry": ["drums"], "Clyde Lombardi": ["bass"], "Al Haig": ["piano"]}, "instrument": ["tenor saxophone"], "year": "1948", "label-id": "Mainstream MDCD 722"}, {"album": "Live Performances", "artist": "Charlie Parker", "personnel": {"Miles Davis": ["trumpet"], "Max Roach": ["drums"], "Tommy Potter": ["bass"], "Al Haig": ["piano"]}, "instrument": ["alto saxophone"], "year": "1948", "label-id": "ESP-Disk' ESP 3000"}, {"album": "Charlie Parker On The Air, Vol. 1", "artist": "Charlie Parker", "personnel": {"Miles Davis": ["trumpet"], "Max Roach": ["drums"], "Tommy Potter": ["bass"], "Al Haig": ["piano"]}, "instrument": ["alto saxophone"], "year": "1948", "label-id": "Everest FS 214"}, {"album": "Broadcast Performances, Vol. 2", "artist": "Charlie Parker", "personnel": {"Kenny Dorham": ["trumpet"], "Max Roach": ["drums"], "Tommy Potter": ["bass"], "Al Haig": ["piano"]}, "instrument": ["alto saxophone"], "year": "1949", "label-id": "ESP-Disk' ESP 3001"}, {"album": "Bird At The Roost, Vol. 2", "artist": "Charlie Parker", "personnel": {"Kenny Dorham": ["trumpet"], "Joe Harris": ["drums"], "Tommy Potter": ["bass"], "Al Haig": ["piano"]}, "instrument": ["alto saxophone"], "year": "1949", "label-id": "Savoy ZDS 4413/14"}, {"album": "Jam 1949 \u00a0(Royal Jazz", "artist": "Miles Davis", "personnel": {"Shelly Manne": ["drums"], "Al Haig": ["piano"], "Buddy DeFranco": ["clarinet"], "Charlie Ventura": ["tenor", "baritone saxophone"], "Kai Winding": ["trombone"], "Lucky Thompson": ["tenor saxophone"], "Oscar Pettiford": ["bass"]}, "instrument": ["trumpet"], "year": "1949", "label-id": "D) RJD 514"}, {"album": "When The Red, Red Robin Comes Bob, Bob, Bobbin' Along / Beban Cubop", "artist": "Dave Lambert", "personnel": {"Curly Russell": ["bass"], "Diego Ibarra": ["bongos"], "Al Haig": ["piano"], "Max Roach": ["drums"], "Vidal Bolado": ["congas"]}, "instrument": ["vocals"], "year": "1949", "label-id": "Capitol 60014"}, {"album": "Hawaiian War Chant / Always", "artist": "Dave Lambert", "personnel": {"Curly Russell": ["bass"], "Diego Ibarra": ["bongos"], "Al Haig": ["piano"], "Max Roach": ["drums"], "Vidal Bolado": ["congas"]}, "instrument": ["vocals"], "year": "1949", "label-id": "Capitol 60011"}, {"album": "Birth Of The Cool", "artist": "Miles Davis", "personnel": {"Joe Schulman": ["bass"], "Al Haig": ["piano"], "Bill Barber": ["tuba"], "Gerry Mulligan": ["baritone saxophone", "arranger"], "Junior Collins": ["french horn"], "Max Roach": ["drums"], "Kai Winding": ["trombone"], "John Lewis": ["arranger"], "Lee Konitz": ["alto saxophone"]}, "instrument": ["trumpet"], "year": "1949", "label-id": "Capitol T 792"}, {"album": "Bird At The Roost", "artist": "Charlie Parker", "personnel": {"Kenny Dorham": ["trumpet"], "Max Roach": ["drums"], "Tommy Potter": ["bass"], "Al Haig": ["piano"]}, "instrument": ["alto saxophone"], "year": "1949", "label-id": "Savoy SJL 1108"}, {"album": "Alto Saxes", "personnel": {"Charlie Parker": ["alto saxophone"], "Al Haig": ["piano"], "Kenny Dorham": ["trumpet"], "Max Roach": ["drums"], "Tommy Potter": ["bass"], "Carlos Vidal": ["bongos"], "Tommy Turk": ["trombone"]}, "artist": "Various Artists", "label-id": "Norgran MGN 1035", "year": "1949"}, {"album": "Jazz Perennial", "artist": "Charlie Parker", "personnel": {"Al Haig": ["piano"], "Kenny Dorham": ["trumpet"], "Max Roach": ["drums"], "Tommy Potter": ["bass"], "Carlos Vidal": ["bongos"], "Tommy Turk": ["trombone"]}, "instrument": ["alto saxophone"], "year": "1949", "label-id": "Verve MGV 8009"}, {"album": "Bird On The Road", "artist": "Charlie Parker", "personnel": {"Al Haig": ["piano"], "Kenny Dorham": ["trumpet"], "Max Roach": ["drums"], "Tommy Potter": ["bass"], "Milt Jackson": ["vibraphone"], "Lucky Thompson": ["tenor saxophone"]}, "instrument": ["alto saxophone"], "year": "1949", "label-id": "Jazz Showcase 5003"}, {"album": "Al Haig Trio And Sextets", "artist": "Al Haig", "personnel": {"Wardell Gray": ["tenor saxophone"], "Terry Swope": ["vocals"], "Jimmy Raney": ["guitar"], "Tommy Potter": ["bass"], "Roy Haynes": ["drums"]}, "instrument": ["piano"], "year": "1949", "label-id": "Original Jazz Classics OJCCD 1929-2"}, {"album": "Tenors Anyone", "personnel": {"Wardell Gray": ["tenor saxophone"], "Jimmy Raney": ["guitar"], "Tommy Potter": ["bass"], "Roy Haynes": ["drums"], "Al Haig": ["piano"]}, "artist": "Various Artists", "label-id": "Dawn DLP 1126", "year": "1949"}, {"album": "Bird And Diz \u00a0(Universal", "artist": "Charlie Parker", "personnel": {"Kenny Dorham": ["trumpet"], "Max Roach": ["drums"], "Tommy Potter": ["bass"], "Al Haig": ["piano"]}, "instrument": ["alto saxophone"], "year": "1949", "label-id": "J) UCCV 9034"}, {"album": "Bird In Paris", "artist": "Charlie Parker", "personnel": {"Kenny Dorham": ["trumpet"], "Max Roach": ["drums"], "Tommy Potter": ["bass"], "Al Haig": ["piano"]}, "instrument": ["alto saxophone"], "year": "1949", "label-id": "Bird In Paris CP 3"}, {"album": "Charlie Parker In France 1949 \u00a0(Jazz O.P.", "artist": "Charlie Parker", "personnel": {"Kenny Dorham": ["trumpet"], "Max Roach": ["drums"], "Tommy Potter": ["bass"], "Al Haig": ["piano"]}, "instrument": ["alto saxophone"], "year": "1949", "label-id": "F) OMS 7004"}, {"album": "2 Giants \u00a0(Vogue", "artist": "Max Roach", "personnel": {"Kenny Dorham": ["trumpet"], "Tommy Potter": ["bass"], "James Moody": ["tenor saxophone"], "Al Haig": ["piano"]}, "instrument": ["drums"], "year": "1949", "label-id": "F) LDA 16008"}, {"album": "Al Haig Trio And Quintet", "artist": "Al Haig", "personnel": {"Kenny Dorham": ["trumpet"], "Max Roach": ["drums"], "Tommy Potter": ["bass"], "James Moody": ["tenor saxophone"]}, "instrument": ["piano"], "year": "1949", "label-id": "Prestige PR 7841"}, {"album": "In The Beginning: Jazz Legacy 47 \u00a0(Jazz Legacy", "personnel": {"Kenny Dorham": ["trumpet"], "Max Roach": ["drums"], "Tommy Potter": ["bass"], "Al Haig": ["piano"]}, "artist": "James Moody", "label-id": "F) JL 97", "year": "1949"}, {"album": "Stan Getz Quartets", "artist": "Stan Getz", "personnel": {"Gene Ramey": ["bass"], "Stan Levey": ["drums"], "Al Haig": ["piano"]}, "instrument": ["tenor saxophone"], "year": "1949", "label-id": "Prestige PRLP 7002"}, {"album": "Conception", "personnel": {"Gene Ramey": ["bass"], "Stan Getz": ["tenor saxophone"], "Stan Levey": ["drums"], "Al Haig": ["piano"]}, "artist": "Various Artists", "label-id": "Prestige PRLP 7013", "year": "1949"}, {"album": "Gee How You Thrill Me / Once In A While", "personnel": {"Jimmy Raney": ["guitar"], "Roy Haynes": ["drums"], "Danny Payne": ["vocals"], "Tommy Potter": ["bass"], "Al Haig": ["piano"]}, "artist": "Danny Payne/Al Haig", "label-id": "Discovery 516", "year": "1949"}, {"album": "My Mother's Birthday / World Of My Own", "personnel": {"Jimmy Raney": ["guitar"], "Roy Haynes": ["drums"], "Danny Payne": ["vocals"], "Tommy Potter": ["bass"], "Al Haig": ["piano"]}, "artist": "Danny Payne/Al Haig", "label-id": "Discovery 508", "year": "1949"}, {"album": "Autumn Serenade / The Lam Is Low", "personnel": {"Jimmy Raney": ["guitar"], "Roy Haynes": ["drums"], "Tommy Potter": ["bass"], "Junior Daniels": ["vocals"], "Al Haig": ["piano"]}, "artist": "Junior Daniels/Al Haig", "label-id": "Discovery 507", "year": "1949"}, {"album": "Prezervation", "personnel": {"Al Haig": ["piano"], "Jimmy Raney": ["guitar", "guitar", "vocals"], "Stan Getz": ["tenor saxophone"], "Tommy Potter": ["bass"], "Roy Haynes": ["drums"], "Blossom Dearie": ["vocals"], "Kai Winding": ["trombone"]}, "artist": "Stan Getz/Al Haig", "label-id": "Prestige PR 7516", "year": "1949"}, {"album": "The Big Head / Platinum Love", "artist": "Coleman Hawkins", "personnel": {"Nelson Boyd": ["bass"], "Shadow Wilson": ["drums"], "John Collins": ["guitar"], "Cecil Payne": ["baritone saxophone"], "Al Haig": ["piano"], "J.J. Johnson": ["trombone"], "Bennie Green": ["trombone"]}, "instrument": ["tenor saxophone"], "year": "1949", "label-id": "Mercury 8909x45"}, {"album": "Skippy / There's A Small Hotel", "artist": "Coleman Hawkins", "personnel": {"Nelson Boyd": ["bass"], "Shadow Wilson": ["drums"], "John Collins": ["guitar"], "Cecil Payne": ["baritone saxophone"], "Al Haig": ["piano"], "J.J. Johnson": ["trombone"], "Bennie Green": ["trombone"]}, "instrument": ["tenor saxophone"], "year": "1949", "label-id": "Mercury 8912x45"}, {"album": "Tenor Saxes", "personnel": {"Nelson Boyd": ["bass"], "Shadow Wilson": ["drums"], "John Collins": ["guitar"], "Cecil Payne": ["baritone saxophone"], "Al Haig": ["piano"], "J.J. Johnson": ["trombone"], "Bennie Green": ["trombone"], "Coleman Hawkins": ["tenor saxophone"]}, "artist": "Various Artists", "label-id": "Norgran MGN 1034", "year": "1949"}, {"album": "The Anatomy Of Improvisation", "personnel": {"Nelson Boyd": ["bass"], "Shadow Wilson": ["drums"], "John Collins": ["guitar"], "Cecil Payne": ["baritone saxophone"], "Al Haig": ["piano"], "J.J. Johnson": ["trombone"], "Bennie Green": ["trombone"], "Coleman Hawkins": ["tenor saxophone"]}, "artist": "Various Artists", "label-id": "Verve MGV 8230", "year": "1949"}, {"album": "25 Years Of Prestige", "personnel": {"Tommy Potter": ["bass"], "Max Roach": ["drums"], "Al Haig": ["piano"], "Don Lanphere": ["tenor saxophone"], "Fats Navarro": ["trumpet"]}, "artist": "Various Artists", "label-id": "Prestige PR 24046", "year": "1949"}, {"album": "Trumpet Giants", "artist": "Fats Navarro", "personnel": {"Tommy Potter": ["bass"], "Max Roach": ["drums"], "Al Haig": ["piano"], "Don Lanphere": ["tenor saxophone"]}, "instrument": ["trumpet"], "year": "1949", "label-id": "New Jazz NJLP 8296"}, {"album": "Prestige First Sessions, Vol. 1", "personnel": {"Tommy Potter": ["bass"], "Max Roach": ["drums"], "Al Haig": ["piano"], "Don Lanphere": ["tenor saxophone"], "Fats Navarro": ["trumpet"]}, "artist": "Don Lanphere/Fats Navarro/Leo Parker/Al Haig", "label-id": "Prestige PRCD 24114-2", "year": "1949"}, {"album": "Central Avenue", "artist": "Wardell Gray", "personnel": {"Roy Haynes": ["drums"], "Tommy Potter": ["bass"], "Al Haig": ["piano"]}, "instrument": ["tenor saxophone"], "year": "1949", "label-id": "Prestige P 24062"}, {"album": "Wardell Gray Memorial, Vol. 1", "artist": "Wardell Gray", "personnel": {"Roy Haynes": ["drums"], "Tommy Potter": ["bass"], "Al Haig": ["piano"]}, "instrument": ["tenor saxophone"], "year": "1949", "label-id": "Prestige PRLP 7008"}, {"album": "Wardell Gray Memorial, Vol. 1", "artist": "Wardell Gray", "personnel": {"Roy Haynes": ["drums"], "Tommy Potter": ["bass"], "Al Haig": ["piano"]}, "instrument": ["tenor saxophone"], "year": "1949", "label-id": "Original Jazz Classics OJCCD 050-2"}, {"album": "Bird's Eyes, Vol. 2 \u00a0(Philology", "artist": "Charlie Parker", "personnel": {"Tommy Potter": ["bass"], "Max Roach": ["drums"], "Red Rodney": ["trumpet"], "Al Haig": ["piano"]}, "instrument": ["alto saxophone"], "year": "1949", "label-id": "It) 214 W 12"}, {"album": "Bird's Eyes, Vol. 3 \u00a0(Philology", "artist": "Charlie Parker", "personnel": {"Tommy Potter": ["bass"], "Max Roach": ["drums"], "Red Rodney": ["trumpet"], "Al Haig": ["piano"]}, "instrument": ["alto saxophone"], "year": "1949", "label-id": "It) 214 W 15"}, {"album": "Stars Of Modern Jazz Concert At Carnegie Hall", "personnel": {"Roy Haynes": ["drums"], "Tommy Potter": ["bass"], "Stan Getz": ["tenor saxophone"], "Kai Winding": ["trombone"], "Al Haig": ["piano"]}, "artist": "Various Artists", "label-id": "IAJRC 20", "year": "1949"}, {"album": "Dance Of The Infidels", "artist": "Charlie Parker", "personnel": {"Roy Haynes": ["drums"], "Tommy Potter": ["bass"], "Red Rodney": ["trumpet"], "Al Haig": ["piano"]}, "instrument": ["alto saxophone"], "year": "1949", "label-id": "S.C.A.M. JPG 1"}, {"album": "Stan Getz, Vol. 2", "artist": "Stan Getz", "personnel": {"Roy Haynes": ["drums"], "Tommy Potter": ["bass"], "Al Haig": ["piano"]}, "instrument": ["tenor saxophone"], "year": "1950", "label-id": "Prestige PRLP 104"}, {"album": "Herbie Steward \u00a0(Vogue", "artist": "Herbie Steward", "personnel": {"Jimmy Raney": ["guitar"], "Roy Haynes": ["drums"], "Curly Russell": ["bass"], "Al Haig": ["piano"]}, "instrument": ["tenor saxophone"], "year": "1950", "label-id": "E) EPV 1085"}, {"album": "'Tain't No Use / Sinbad The Tailor", "artist": "Herbie Steward", "personnel": {"Jimmy Raney": ["guitar"], "Roy Haynes": ["drums"], "Curly Russell": ["bass"], "Al Haig": ["piano"]}, "instrument": ["tenor saxophone"], "year": "1950", "label-id": "Roost 510"}, {"album": "I Cried For You / Until The Real Thing Comes Along", "artist": "Mary Ann McCall", "personnel": {"Curly Russell": ["bass"], "Al Haig": ["piano"], "Al Cohn": ["tenor saxophone", "arranger"], "Jeff Morton": ["drums"], "Red Rodney": ["trumpet"], "Gerry Mulligan": ["baritone saxophone"], "Earl Swope": ["trombone"]}, "instrument": ["vocals"], "year": "1950", "label-id": "Roost 514"}, {"album": "The Sky Is Crying / After I Say I'm Sorry", "artist": "Mary Ann McCall", "personnel": {"Curly Russell": ["bass"], "Al Haig": ["piano"], "Al Cohn": ["tenor saxophone", "arranger"], "Jeff Morton": ["drums"], "Red Rodney": ["trumpet"], "Gerry Mulligan": ["baritone saxophone"], "Earl Swope": ["trombone"]}, "instrument": ["vocals"], "year": "1950", "label-id": "Roost 511"}, {"album": "Charlie Parker Live Birdland 1950 \u00a0(EPM Musique", "artist": "Charlie Parker", "personnel": {"Al Haig": ["piano"], "Tommy Potter": ["bass"], "J.J. Johnson": ["trombone"], "Roy Haynes": ["drums"], "Red Rodney": ["trumpet"]}, "instrument": ["alto saxophone"], "year": "1950", "label-id": "F) FDC 5710"}, {"album": "Bird At St. Nick's", "artist": "Charlie Parker", "personnel": {"Roy Haynes": ["drums"], "Tommy Potter": ["bass"], "Red Rodney": ["trumpet"], "Al Haig": ["piano"]}, "instrument": ["alto saxophone"], "year": "1950", "label-id": "Jazz Workshop JWS 500"}, {"album": "Charlie Parker At The Apollo Theater And St. Nick's Arena", "artist": "Charlie Parker", "personnel": {"Roy Haynes": ["drums"], "Tommy Potter": ["bass"], "Red Rodney": ["trumpet"], "Al Haig": ["piano"]}, "instrument": ["alto saxophone"], "year": "1950", "label-id": "Zim ZM 1007"}, {"album": "The Complete Roost Recordings", "artist": "Stan Getz", "personnel": {"Roy Haynes": ["drums"], "Tommy Potter": ["bass"], "Al Haig": ["piano"]}, "instrument": ["tenor saxophone"], "year": "1950", "label-id": "Roost 7243 8 59622 2"}, {"album": "The Getz Age", "artist": "Stan Getz", "personnel": {"Roy Haynes": ["drums"], "Tommy Potter": ["bass"], "Al Haig": ["piano"]}, "instrument": ["tenor saxophone"], "year": "1950", "label-id": "Roost RLP 2258"}, {"album": "The Sound", "artist": "Stan Getz", "personnel": {"Roy Haynes": ["drums"], "Tommy Potter": ["bass"], "Al Haig": ["piano"]}, "instrument": ["tenor saxophone"], "year": "1950", "label-id": "Roost RLP 2207"}, {"album": "50", "artist": "Charlie Parker", "personnel": {"Al Haig": ["piano"], "Kenny Dorham": ["trumpet"], "Tommy Potter": ["bass"], "Tony Scott": ["clarinet"], "Roy Haynes": ["drums"], "possibly Red Rodney": ["trumpet"]}, "instrument": ["alto saxophone"], "year": "1950", "label-id": "Grotto 495"}, {"album": "Ballads And Birdland \u00a0(Klacto", "artist": "Charlie Parker", "personnel": {"Al Haig": ["piano"], "Kenny Dorham": ["trumpet"], "Tommy Potter": ["bass"], "Tony Scott": ["clarinet"], "Roy Haynes": ["drums"], "possibly Red Rodney": ["trumpet"]}, "instrument": ["alto saxophone"], "year": "1950", "label-id": "E) MG 101"}, {"album": "Just Friends", "artist": "Charlie Parker", "personnel": {"Al Haig": ["piano"], "Kenny Dorham": ["trumpet"], "Tommy Potter": ["bass"], "Tony Scott": ["clarinet"], "Roy Haynes": ["drums"], "possibly Red Rodney": ["trumpet"]}, "instrument": ["alto saxophone"], "year": "1950", "label-id": "S.C.A.M. JPG 4"}, {"album": "50", "personnel": {"Jack \"The Bear\" Parker": ["drums"], "Leo Parker": ["baritone", "alto saxophone"], "Max Roach": ["drums"], "Oscar Pettiford": ["bass"], "Al Haig": ["piano"]}, "artist": "Various Artists - Fisrt Sessions 1949", "label-id": "Prestige P 24081", "year": "1950"}, {"album": "Parker Plus Strings", "artist": "Charlie Parker", "personnel": {"3 violins": ["arranger"], "Al Haig or Bernie Leighton": ["piano"], "Tommy Potter": ["bass"], "1 oboe": ["arranger"], "Roy Haynes": ["drums"], "Jimmy Mundy": ["arranger"], "1 viola": ["arranger"], "1 harp": ["arranger"], "1 cello": ["arranger"]}, "instrument": ["alto saxophone"], "year": "1950", "label-id": "Charlie Parker CP 513"}, {"album": "Bird With Strings Live At The Apollo, Carnegie Hall And Birdland", "artist": "Charlie Parker", "personnel": {"3 violins": ["arranger"], "Al Haig or Bernie Leighton": ["piano"], "Tommy Potter": ["bass"], "1 oboe": ["arranger"], "Roy Haynes": ["drums"], "Jimmy Mundy": ["arranger"], "1 viola": ["arranger"], "1 harp": ["arranger"], "1 cello": ["arranger"]}, "instrument": ["alto saxophone"], "year": "1950", "label-id": "Columbia JC 34832"}, {"album": "Norman Granz Jazz Concert", "personnel": {"Roy Haynes": ["drums"], "Tommy Mace": ["oboe"], "Charlie Parker": ["alto saxophone"], "Al Haig": ["piano"], "Sam Kaplan": ["violin"], "Wallace McManus": ["harp"], "Tommy Potter": ["bass"], "Bill Rundy": ["cello"], "Stan Karpenia": ["violin"], "Ted Bloom": ["violin"], "Dave Uchitel": ["viola"]}, "artist": "Norman Granz Jazz Concert", "label-id": "Norgran MGN 3501-2", "year": "1950"}, {"album": "Apartment Jam Sessions", "artist": "Charlie Parker", "personnel": {"Jimmy Knepper": ["trombone"], "Al Haig": ["piano"], "unknown": ["bass"], "John Nielson": ["trumpet"], "Don Lanphere": ["tenor saxophone"], "Frank Isola": ["drums"], "Joe Maini": ["alto saxophone"]}, "instrument": ["alto saxophone"], "year": "1950", "label-id": "Zim ZM 1006"}, {"album": "Stan Getz At Storyville", "artist": "Stan Getz", "personnel": {"Jimmy Raney": ["guitar"], "Teddy Kotick": ["bass"], "Tiny Kahn": ["drums"], "Al Haig": ["piano"]}, "instrument": ["tenor saxophone"], "year": "1951", "label-id": "Roost RLP 2209"}, {"album": "Stan Getz At Storyville, Vol. 2", "artist": "Stan Getz", "personnel": {"Jimmy Raney": ["guitar"], "Teddy Kotick": ["bass"], "Tiny Kahn": ["drums"], "Al Haig": ["piano"]}, "instrument": ["tenor saxophone"], "year": "1951", "label-id": "Roost RLP 2225"}, {"album": "Billie And Stan", "personnel": {"Billie Holiday": ["vocals"], "Teddy Kotick": ["bass"], "Jimmy Raney": ["guitar"], "Stan Getz": ["tenor saxophone"], "Al Haig": ["piano"], "Tiny Kahn": ["drums"]}, "artist": "Billie Holiday/Stan Getz", "label-id": "Dale LP 25", "year": "1951"}, {"album": "1952", "artist": "Billie Holiday", "personnel": {"Jimmy Raney": ["guitar"], "Teddy Kotick": ["bass"], "Tiny Kahn": ["drums"], "Al Haig": ["piano"]}, "instrument": ["vocals"], "year": "1951", "label-id": "ESP-Disk' ESP 3002"}, {"album": "52", "personnel": {"Harry Babasin": ["bass", "leader"], "Charlie Parker": ["alto saxophone"], "Al Haig": ["piano"], "Chet Baker": ["trumpet"], "Lawrence Marable": ["drums"], "Sonny Criss": ["alto saxophone"]}, "artist": "Harry Babasin/Sonny Criss/Chet Baker/Charlie Parker/Al Haig/Laurance Marable - Inglewood Jam 6-16", "label-id": "Jazz Chronicles JCS-102", "year": "1952"}, {"album": "Live In Hollywood", "artist": "Al Haig", "personnel": {"Larry Bunker": ["drums"], "Chet Baker": ["trumpet"], "Les Thompson": ["harmonica"], "Jack Montrose": ["tenor saxophone"], "Ted Ottison": ["trumpet"], "Dave Bryant": ["bass"], "Sonny Criss": ["alto saxophone"]}, "instrument": ["piano"], "year": "1952", "label-id": "Xanadu 206"}, {"album": "Jazz Pianists Galore", "personnel": {"Harry Babasin": ["bass", "cello"], "Larry Bunker": ["drums", "vibraphone"], "Al Haig": ["piano"]}, "artist": "Various Artists", "label-id": "Pacific Jazz JWC-506", "year": "1952"}, {"album": "How About You / Saunders Meanders", "artist": "Harry Babasin", "personnel": {"Larry Bunker": ["drums", "vibraphone"], "Bob Enevoldsen": ["tenor saxophone", "valve trombone", "bass"], "Al Haig": ["piano"]}, "instrument": ["bass", "cello"], "year": "1952", "label-id": "Pacific Jazz 603"}, {"album": "Al Haig 1953 \u00a0(Jazzbank Archives", "artist": "Al Haig", "personnel": {"Stan Levey": ["drums"], "Richie Kamuca": ["tenor saxophone"], "Frank Rosolino": ["trombone"], "Conte Candoli": ["trumpet"], "Don Bagley": ["bass"], "Lee Konitz": ["alto saxophone"]}, "instrument": ["piano"], "year": "1953", "label-id": "J) MTCJ-1040"}, {"album": "Now's The Time", "artist": "Charlie Parker", "personnel": {"Percy Heath": ["bass"], "Max Roach": ["drums"], "Al Haig": ["piano"]}, "instrument": ["alto saxophone"], "year": "1953", "label-id": "Verve MGV 8005"}, {"album": "Bird \u00a0(Verve", "artist": "Charlie Parker", "personnel": {"Percy Heath": ["bass"], "Max Roach": ["drums"], "Al Haig": ["piano"]}, "instrument": ["alto saxophone"], "year": "1953", "label-id": "J) J00J-29001/10"}, {"album": "The Quartet Of Charlie Parker", "artist": "Charlie Parker", "personnel": {"Percy Heath": ["bass"], "Max Roach": ["drums"], "Al Haig": ["piano"]}, "instrument": ["alto saxophone"], "year": "1953", "label-id": "Verve 825 671-2"}, {"album": "Wisp", "artist": "Al Haig", "personnel": {"Bill Crow": ["bass"], "Lee Abrams": ["drums"]}, "instrument": ["piano"], "year": "1954", "label-id": "Counterpoint CPT 551"}, {"album": "Piano: The Many Faces Of Jazz, Vol. 3 \u00a0(Mode", "personnel": {"Bill Crow": ["bass"], "Lee Abrams": ["drums"], "Al Haig": ["piano"]}, "artist": "Various Artists", "label-id": "F) CMDINT 9515", "year": "1954"}, {"album": "Al Haig Quartet", "artist": "Al Haig", "personnel": {"Phil Brown": ["drums"], "Teddy Kotick": ["bass"], "Benny Weeks": ["guitar"]}, "instrument": ["piano"], "year": "1954", "label-id": "Period SPL 1104"}, {"album": "Trumpet Geniuses Of Fifties: Black And White Series, Vol. 1 \u00a0(Philology", "artist": "Chet Baker", "personnel": {"Bob Neel": ["drums"], "Phil Urso": ["tenor saxophone"], "Carson Smith": ["bass"], "Al Haig": ["piano"]}, "instrument": ["trumpet"], "year": "1954", "label-id": "It) 214 W 13"}, {"album": "The Young Bloods", "personnel": {"Charlie Persip": ["drums"], "Al Haig": ["piano"], "Teddy Kotick": ["bass"], "Donald Byrd": ["trumpet"], "Phil Woods": ["alto saxophone"]}, "artist": "Phil Woods/Donald Byrd", "label-id": "Prestige PRLP 7080", "year": "1956"}, {"album": "Chet Baker In New York", "artist": "Chet Baker", "personnel": {"Johnny Griffin": ["tenor saxophone"], "Philly Joe Jones": ["drums"], "Paul Chambers": ["bass"], "Al Haig": ["piano"]}, "instrument": ["trumpet"], "year": "1958", "label-id": "Riverside RLP 12-281"}, {"album": "New Blue Horns", "personnel": {"Chet Baker": ["trumpet"], "Philly Joe Jones": ["drums"], "Paul Chambers": ["bass"], "Al Haig": ["piano"]}, "artist": "Various Artists", "label-id": "Riverside RLP 12-294", "year": "1958"}, {"album": "Al Haig Today!", "artist": "Al Haig", "personnel": {"Ed DeHaas": ["bass"], "Jim Kappes": ["drums"]}, "instrument": ["piano"], "year": "1965", "label-id": "Mint AL 711"}, {"album": "Invitation \u00a0(Spotlite (E) SPJLP 4", "artist": "Al Haig", "personnel": {"Gilbert \"Bibi\" Rovere": ["bass"], "Kenny Clarke": ["drums"]}, "instrument": ["piano"], "year": "1974", "label-id": "AH 4)"}, {"album": "Strings Attached", "artist": "Al Haig", "personnel": {"Jimmy Raney": ["guitar"], "Frank Gant": ["drums"], "Doug Raney": ["guitar"], "Jamil Nasser": ["bass"]}, "instrument": ["piano"], "year": "1975", "label-id": "Choice CRS 1010"}, {"album": "Strings Attached \u00a0(Absord Music Japan", "artist": "Al Haig", "personnel": {"Jimmy Raney": ["guitar"], "Frank Gant": ["drums"], "Jamil Nasser": ["bass"]}, "instrument": ["piano"], "year": "1975", "label-id": "J) ABCJ-146"}, {"album": "Duke 'N' Bird \u00a0(East Wind", "artist": "Al Haig", "personnel": {}, "instrument": ["piano"], "year": "1976", "label-id": "J) UCCJ 9069"}, {"album": "Interplay", "artist": "Al Haig", "personnel": {"Jamil Nasser": ["bass"]}, "instrument": ["piano"], "year": "1976", "label-id": "Seabreeze SB 1005"}, {"album": "I Love You \u00a0(Century", "artist": "Al Haig", "personnel": {"Jimmy Wormworth": ["drums"], "Jamil Nasser": ["bass"]}, "instrument": ["piano"], "year": "1977", "label-id": "J) CECC00281"}, {"album": "A Portrait Of Bud Powell \u00a0(Absord Music Japan", "artist": "Al Haig", "personnel": {"Frank Gant": ["drums"], "Jamil Nasser": ["bass"]}, "instrument": ["piano"], "year": "1977", "label-id": "J) ABCJ-66"}, {"album": "Ornithology", "artist": "Al Haig", "personnel": {"Frank Gant": ["drums"], "Jamil Nasser": ["bass"]}, "instrument": ["piano"], "year": "1977", "label-id": "Progressive PCD-7024"}, {"album": "Stablemates \u00a0(Spotlite", "personnel": {"Jon Eardley": ["trumpet", "flugelhorn"], "Daryl Runswick": ["bass"], "Art Themen": ["tenor saxophone"], "Allan Ganley": ["drums"], "Al Haig": ["piano"]}, "artist": "Jon Eardley/Al Haig", "label-id": "E) SPJLP 11", "year": "1977"}, {"album": "They All Played Bebop", "personnel": {"Henri Renaud": ["producer"], "Jimmy Wormworth": ["drums"], "Jamil Nasser": ["bass"], "Al Haig": ["piano"]}, "artist": "Various Artists", "label-id": "Columbia C2 38039", "year": "1977"}, {"album": "I Remember Bebop", "personnel": {"Henri Renaud": ["producer"], "Al Haig": ["piano"]}, "artist": "Various Artists", "label-id": "Columbia C2 35381", "year": "1977"}, {"album": "Expressly Ellington \u00a0(Spotlite", "artist": "Al Haig", "personnel": {"Tony Mann": ["drums"], "Art Themen": ["tenor saxophone"], "Jamil Nasser": ["bass"]}, "instrument": ["piano"], "year": "1978", "label-id": "E) SPJLP 20"}, {"album": "Un Poco Loco \u00a0(Spotlite", "artist": "Al Haig", "personnel": {"Tony Mann": ["drums"], "Jamil Nasser": ["bass"]}, "instrument": ["piano"], "year": "1978", "label-id": "E) SPJ 701 CD"}, {"album": "Blue Manhattan \u00a0(Venus", "artist": "Al Haig", "personnel": {"Frank Gant": ["drums"], "Reggie Johnson": ["bass"]}, "instrument": ["piano"], "year": "1980", "label-id": "J) TKCZ-79513"}, {"album": "Bebop Live (Blue) \u00a0(Spotlite", "personnel": {"Peter King": ["alto saxophone"], "Kenny Baldock": ["bass"], "Art Themen": ["tenor", "soprano saxophone"], "Allan Ganley": ["drums"], "Al Haig": ["piano"]}, "artist": "University College School All Stars", "label-id": "E) SPJLP 23", "year": "1982"}, {"album": "Bebop Live (Red) \u00a0(Spotlite", "personnel": {"Peter King": ["alto saxophone"], "Kenny Baldock": ["bass"], "Art Themen": ["tenor", "soprano saxophone"], "Allan Ganley": ["drums"], "Al Haig": ["piano"]}, "artist": "University College School All Stars", "label-id": "E) SPJ 303 CD", "year": "1982"}]